heatmappy/__init__.py
heatmappy/heatmap.py
heatmappy/video.py
heatmappy/assets/450pxdot.png
heatmappy/assets/SampleVideo_720x480_1mb.mp4
heatmappy/assets/cat.jpg
heatmappy/assets/default.png
heatmappy/assets/reveal.png
heatmappy_vnpt-0.2.6.dist-info/LICENSE
heatmappy_vnpt-0.2.6.dist-info/METADATA
heatmappy_vnpt-0.2.6.dist-info/WHEEL
heatmappy_vnpt-0.2.6.dist-info/top_level.txt
heatmappy_vnpt-0.2.6.dist-info/RECORD
